{
    "@context": "http://iiif.io/api/presentation/3/context.json",
    "id": "https://globalise-huygens.github.io/datasprint-amh/manifests/4.VEL/1132.json",
    "type": "Manifest",
    "label": {
        "nl": [
            "Affteeckeningh van 't bouwlant in de Vuyle bocht."
        ]
    },
    "metadata": [
        {
            "label": {
                "nl": [
                    "Identifier"
                ]
            },
            "value": {
                "en": [
                    "1132"
                ]
            }
        },
        {
            "label": {
                "nl": [
                    "Date"
                ]
            },
            "value": {
                "en": [
                    "1671"
                ]
            }
        },
        {
            "label": {
                "nl": [
                    "Permalink"
                ]
            },
            "value": {
                "en": [
                    "<a href=\"http://hdl.handle.net/10648/68c0cb26-8c5d-4155-a7cd-1ef6b6f4a149\">http://hdl.handle.net/10648/68c0cb26-8c5d-4155-a7cd-1ef6b6f4a149</a>"
                ]
            }
        },
        {
            "label": {
                "nl": [
                    "Metadata from the Atlas of Mutual Heritage"
                ]
            },
            "value": {
                "en": [
                    "\n    <strong>Title</strong>: Landschap op Mauritius, genoemd 'De vuyle bocht'<br>\n    <strong>Description</strong>: Titel catalogus Leupe (NA): Affteeckeningh van 't bouwlant in de Vuyle bocht.<br>Notities verso: No. 22. affteeckeningh van't bouwlant in de Vuijle bocht / uit brieven en papieren van de Kaap overgek. in 1671, no. 20 [misschien hoort no. 20 niet bij deze notitie, maar is het een aparte vermelding] / 566 [folionummer in de band ?] / op't eiland Mauritius / 498 pp.<br>Op kaart VEL0332 is goed te zien dat de Vuyle Bhaij, ofwel de Vuyle bocht, dichtbij het Nederlandse fort gelegen is.<br>\n    <strong>URL</strong>: <a href=\"https://www.atlasofmutualheritage.nl/page/5859/landschap-op-mauritius-genoemd-de-vuyle-bocht\">https://www.atlasofmutualheritage.nl/page/5859/landschap-op-mauritius-genoemd-de-vuyle-bocht</a>\n    "
                ]
            }
        }
    ],
    "rights": "https://creativecommons.org/publicdomain/mark/1.0/",
    "seeAlso": [
        {
            "id": "https://globalise-huygens.github.io/datasprint-amh/aggregations/4.VEL/1132.json",
            "type": "ore:Aggregation"
        }
    ],
    "items": [
        {
            "id": "https://globalise-huygens.github.io/datasprint-amh/manifests/4.VEL/1132.json/canvas/p1",
            "type": "Canvas",
            "height": 4423,
            "width": 6269,
            "items": [
                {
                    "id": "https://globalise-huygens.github.io/datasprint-amh/manifests/4.VEL/1132.json/canvas/p1/annotationpage",
                    "type": "AnnotationPage",
                    "items": [
                        {
                            "id": "https://globalise-huygens.github.io/datasprint-amh/manifests/4.VEL/1132.json/canvas/p1/anno",
                            "type": "Annotation",
                            "motivation": "painting",
                            "body": {
                                "id": "https://service.archief.nl/iipsrv?IIIF=/2c/fc/9a/c2/42/b4/43/a3/87/99/34/50/9e/f8/ae/00/3c8f3486-3b62-431b-b3a4-39d0beb8f169.jp2/full/full/0/default.jpg",
                                "type": "Image",
                                "height": 4423,
                                "width": 6269,
                                "service": [
                                    {
                                        "@id": "https://service.archief.nl/iipsrv?IIIF=/2c/fc/9a/c2/42/b4/43/a3/87/99/34/50/9e/f8/ae/00/3c8f3486-3b62-431b-b3a4-39d0beb8f169.jp2",
                                        "@type": "ImageService2",
                                        "profile": "http://iiif.io/api/image/2/level1"
                                    }
                                ],
                                "format": "image/jpeg"
                            },
                            "target": "https://globalise-huygens.github.io/datasprint-amh/manifests/4.VEL/1132.json/canvas/p1"
                        }
                    ]
                }
            ]
        }
    ]
}