{
    "@context": "http://iiif.io/api/presentation/3/context.json",
    "id": "https://globalise-huygens.github.io/datasprint-amh/manifests/4.VEL/1263A.json",
    "type": "Manifest",
    "label": {
        "nl": [
            "Blad 2 (dd 13 november 1741)"
        ]
    },
    "metadata": [
        {
            "label": {
                "nl": [
                    "Identifier"
                ]
            },
            "value": {
                "none": [
                    "1263A"
                ]
            }
        },
        {
            "label": {
                "nl": [
                    "Date"
                ]
            },
            "value": {
                "none": [
                    "?"
                ]
            }
        },
        {
            "label": {
                "nl": [
                    "Permalink"
                ]
            },
            "value": {
                "none": [
                    "<a href=\"http://hdl.handle.net/10648/3462a993-8646-4d25-af55-c95fe70b453b\"></a>"
                ]
            }
        }
    ],
    "rights": "https://creativecommons.org/publicdomain/mark/1.0/",
    "seeAlso": [
        {
            "id": "https://globalise-huygens.github.io/datasprint-amh/aggregations/4.VEL/1263A.json",
            "type": "ore:Aggregation"
        }
    ],
    "items": [
        {
            "id": "https://globalise-huygens.github.io/datasprint-amh/manifests/4.VEL/1263A.json#canvas/p1",
            "type": "Canvas",
            "height": 5148,
            "width": 6656,
            "items": [
                {
                    "id": "https://globalise-huygens.github.io/datasprint-amh/manifests/4.VEL/1263A.json#canvas/p1/annotationpage",
                    "type": "AnnotationPage",
                    "items": [
                        {
                            "id": "https://globalise-huygens.github.io/datasprint-amh/manifests/4.VEL/1263A.json#canvas/p1/anno",
                            "type": "Annotation",
                            "motivation": "painting",
                            "body": {
                                "id": "https://service.archief.nl/iipsrv?IIIF=/57/57/41/bf/38/2c/46/80/bb/48/0d/d8/bb/16/c4/2a/21d91856-5ff5-44bf-a252-f3497d674266.jp2/full/full/0/default.jpg",
                                "type": "Image",
                                "height": 5148,
                                "width": 6656,
                                "service": [
                                    {
                                        "@id": "https://service.archief.nl/iipsrv?IIIF=/57/57/41/bf/38/2c/46/80/bb/48/0d/d8/bb/16/c4/2a/21d91856-5ff5-44bf-a252-f3497d674266.jp2",
                                        "@type": "ImageService2",
                                        "profile": "http://iiif.io/api/image/2/level1"
                                    }
                                ],
                                "format": "image/jpeg"
                            },
                            "target": "https://globalise-huygens.github.io/datasprint-amh/manifests/4.VEL/1263A.json#canvas/p1"
                        }
                    ]
                }
            ]
        }
    ]
}