{
    "@context": "http://iiif.io/api/presentation/3/context.json",
    "id": "https://globalise-huygens.github.io/datasprint-amh/manifests/4.VEL/1413.json",
    "type": "Manifest",
    "label": {
        "nl": [
            "Carte des Antilles Francoises et des Iles Voisines etc."
        ]
    },
    "metadata": [
        {
            "label": {
                "nl": [
                    "Identifier"
                ]
            },
            "value": {
                "none": [
                    "1413"
                ]
            }
        },
        {
            "label": {
                "nl": [
                    "Date"
                ]
            },
            "value": {
                "none": [
                    "?"
                ]
            }
        },
        {
            "label": {
                "nl": [
                    "Permalink"
                ]
            },
            "value": {
                "none": [
                    "<a href=\"http://hdl.handle.net/10648/409a845d-5b99-46f3-82c3-3c84cb983942\"></a>"
                ]
            }
        }
    ],
    "rights": "https://creativecommons.org/publicdomain/mark/1.0/",
    "seeAlso": [
        {
            "id": "https://globalise-huygens.github.io/datasprint-amh/aggregations/4.VEL/1413.json",
            "type": "ore:Aggregation"
        }
    ],
    "items": [
        {
            "id": "https://globalise-huygens.github.io/datasprint-amh/manifests/4.VEL/1413.json#canvas/p1",
            "type": "Canvas",
            "height": 7600,
            "width": 6429,
            "items": [
                {
                    "id": "https://globalise-huygens.github.io/datasprint-amh/manifests/4.VEL/1413.json#canvas/p1/annotationpage",
                    "type": "AnnotationPage",
                    "items": [
                        {
                            "id": "https://globalise-huygens.github.io/datasprint-amh/manifests/4.VEL/1413.json#canvas/p1/anno",
                            "type": "Annotation",
                            "motivation": "painting",
                            "body": {
                                "id": "https://service.archief.nl/iipsrv?IIIF=/af/d0/62/82/80/bd/40/c5/be/42/eb/e3/f5/23/4b/10/79c8389f-c580-4c72-87fd-eb029a165bff.jp2/full/full/0/default.jpg",
                                "type": "Image",
                                "height": 7600,
                                "width": 6429,
                                "service": [
                                    {
                                        "@id": "https://service.archief.nl/iipsrv?IIIF=/af/d0/62/82/80/bd/40/c5/be/42/eb/e3/f5/23/4b/10/79c8389f-c580-4c72-87fd-eb029a165bff.jp2",
                                        "@type": "ImageService2",
                                        "profile": "http://iiif.io/api/image/2/level1"
                                    }
                                ],
                                "format": "image/jpeg"
                            },
                            "target": "https://globalise-huygens.github.io/datasprint-amh/manifests/4.VEL/1413.json#canvas/p1"
                        }
                    ]
                }
            ]
        }
    ]
}