{
    "@context": "http://iiif.io/api/presentation/3/context.json",
    "id": "https://globalise-huygens.github.io/datasprint-amh/manifests/4.VEL/1666D.json",
    "type": "Manifest",
    "label": {
        "nl": [
            "Blad 4"
        ]
    },
    "metadata": [
        {
            "label": {
                "nl": [
                    "Identifier"
                ]
            },
            "value": {
                "en": [
                    "1666D"
                ]
            }
        },
        {
            "label": {
                "nl": [
                    "Date"
                ]
            },
            "value": {
                "en": [
                    "?"
                ]
            }
        },
        {
            "label": {
                "nl": [
                    "Permalink"
                ]
            },
            "value": {
                "en": [
                    "<a href=\"http://hdl.handle.net/10648/0ae48091-ab63-4750-bf74-90cec5c1aeb8\"></a>"
                ]
            }
        },
        {
            "label": {
                "nl": [
                    "Metadata from the Atlas of Mutual Heritage"
                ]
            },
            "value": {
                "en": [
                    "\n    <strong>Title</strong>: Kaart van de rivieren Suriname en Commewijne, detail<br>\n    <strong>Description</strong>: Titel Leupe: \u201cCaerte ofte vertooninge van de Rivieren van Suriname en Commewyne met verscheyde creken uyt deselve spruytende, als Para, Surinoo en Cotteca ende ander meer, gelyck die nu tegenwoordich bewoont verden.\u201d<br>Dit betreft een onderdeel van een reproductie van een zeldzame kaart met de plantages rond the Suriname en Commewijne rivieren. Voor de reproductie in zijn geheel zie VEL1666E.<br>De namen van de drukker en uitgever zijn niet bekend. De originele koperdruk is in 1931 verbrand.<br>Het noorden is onder.<br>Zie Nederlands Archievenblad, jrg. 38 (1930-1931).<br>Schaal van 6 mijlen of 4 Uyren gaens = 140 strepen.<br>\n    <strong>URL</strong>: <a href=\"https://www.atlasofmutualheritage.nl/page/2093/kaart-van-de-rivieren-suriname-en-commewijne-detail\">https://www.atlasofmutualheritage.nl/page/2093/kaart-van-de-rivieren-suriname-en-commewijne-detail</a>\n    "
                ]
            }
        }
    ],
    "rights": "https://creativecommons.org/publicdomain/mark/1.0/",
    "seeAlso": [
        {
            "id": "https://globalise-huygens.github.io/datasprint-amh/aggregations/4.VEL/1666D.json",
            "type": "ore:Aggregation"
        }
    ],
    "items": [
        {
            "id": "https://globalise-huygens.github.io/datasprint-amh/manifests/4.VEL/1666D.json/canvas/p1",
            "type": "Canvas",
            "height": 3584,
            "width": 2796,
            "items": [
                {
                    "id": "https://globalise-huygens.github.io/datasprint-amh/manifests/4.VEL/1666D.json/canvas/p1/annotationpage",
                    "type": "AnnotationPage",
                    "items": [
                        {
                            "id": "https://globalise-huygens.github.io/datasprint-amh/manifests/4.VEL/1666D.json/canvas/p1/anno",
                            "type": "Annotation",
                            "motivation": "painting",
                            "body": {
                                "id": "https://service.archief.nl/iipsrv?IIIF=/e6/db/7a/ec/86/77/4c/0d/a5/9d/39/9e/c8/dc/d0/ce/3e7ca294-a298-4eb0-9add-f91fe94d0ce8.jp2/full/full/0/default.jpg",
                                "type": "Image",
                                "height": 3584,
                                "width": 2796,
                                "service": [
                                    {
                                        "@id": "https://service.archief.nl/iipsrv?IIIF=/e6/db/7a/ec/86/77/4c/0d/a5/9d/39/9e/c8/dc/d0/ce/3e7ca294-a298-4eb0-9add-f91fe94d0ce8.jp2",
                                        "@type": "ImageService2",
                                        "profile": "http://iiif.io/api/image/2/level1"
                                    }
                                ],
                                "format": "image/jpeg"
                            },
                            "target": "https://globalise-huygens.github.io/datasprint-amh/manifests/4.VEL/1666D.json/canvas/p1"
                        }
                    ]
                }
            ]
        }
    ]
}