{
    "@context": "http://iiif.io/api/presentation/3/context.json",
    "id": "https://globalise-huygens.github.io/datasprint-amh/manifests/4.VEL/1778.json",
    "type": "Manifest",
    "label": {
        "nl": [
            "Kaart van de Plantagie La Confiance by de Boekweyt Creeq."
        ]
    },
    "metadata": [
        {
            "label": {
                "nl": [
                    "Identifier"
                ]
            },
            "value": {
                "en": [
                    "1778"
                ]
            }
        },
        {
            "label": {
                "nl": [
                    "Date"
                ]
            },
            "value": {
                "en": [
                    "1735"
                ]
            }
        },
        {
            "label": {
                "nl": [
                    "Permalink"
                ]
            },
            "value": {
                "en": [
                    "<a href=\"http://hdl.handle.net/10648/2ad0f7b4-2177-4016-94a7-0cd0c030da05\">http://hdl.handle.net/10648/2ad0f7b4-2177-4016-94a7-0cd0c030da05</a>"
                ]
            }
        },
        {
            "label": {
                "nl": [
                    "Metadata from the Atlas of Mutual Heritage"
                ]
            },
            "value": {
                "en": [
                    "\n    <strong>Title</strong>: Kaart van de plantage La Confiance aan de Surinamerivier<br>\n    <strong>Description</strong>: Titel Leupe: Kaart van de Plantagie La Confiance by de Boekweyt Creeq.<br>De kaart toont de exacte ligging en omvang van een plantage gelegen aan de rechteroever van de Suriname rivier ('in 't afvaren').<br>De plantage is gelegen bij de Boekwijt kreek.<br>Lengte en breedte zijn in Kettingen aangegeven.<br>Oorsprong: [OBP] Suriname 1736 [fols.] 1283-1284.<br>Schaal van 100 Kettingen a\u0300 66 Rijnlandse v. = 134 strepen.<br>Zie ook de kaarten VEL1777 en VEL1779.<br>\n    <strong>URL</strong>: <a href=\"https://www.atlasofmutualheritage.nl/page/9767/kaart-van-de-plantage-la-confiance-aan-de-surinamerivier\">https://www.atlasofmutualheritage.nl/page/9767/kaart-van-de-plantage-la-confiance-aan-de-surinamerivier</a>\n    "
                ]
            }
        }
    ],
    "rights": "https://creativecommons.org/publicdomain/mark/1.0/",
    "seeAlso": [
        {
            "id": "https://globalise-huygens.github.io/datasprint-amh/aggregations/4.VEL/1778.json",
            "type": "ore:Aggregation"
        }
    ],
    "items": [
        {
            "id": "https://globalise-huygens.github.io/datasprint-amh/manifests/4.VEL/1778.json/canvas/p1",
            "type": "Canvas",
            "height": 4846,
            "width": 3821,
            "items": [
                {
                    "id": "https://globalise-huygens.github.io/datasprint-amh/manifests/4.VEL/1778.json/canvas/p1/annotationpage",
                    "type": "AnnotationPage",
                    "items": [
                        {
                            "id": "https://globalise-huygens.github.io/datasprint-amh/manifests/4.VEL/1778.json/canvas/p1/anno",
                            "type": "Annotation",
                            "motivation": "painting",
                            "body": {
                                "id": "https://service.archief.nl/iipsrv?IIIF=/14/3c/bc/47/37/0e/40/68/bf/24/fd/09/f2/44/f2/e1/38eee0e7-c4a6-4cc9-addf-ed56d99e2040.jp2/full/full/0/default.jpg",
                                "type": "Image",
                                "height": 4846,
                                "width": 3821,
                                "service": [
                                    {
                                        "@id": "https://service.archief.nl/iipsrv?IIIF=/14/3c/bc/47/37/0e/40/68/bf/24/fd/09/f2/44/f2/e1/38eee0e7-c4a6-4cc9-addf-ed56d99e2040.jp2",
                                        "@type": "ImageService2",
                                        "profile": "http://iiif.io/api/image/2/level1"
                                    }
                                ],
                                "format": "image/jpeg"
                            },
                            "target": "https://globalise-huygens.github.io/datasprint-amh/manifests/4.VEL/1778.json/canvas/p1"
                        }
                    ]
                }
            ]
        }
    ]
}