{
    "@context": "http://iiif.io/api/presentation/3/context.json",
    "id": "https://globalise-huygens.github.io/datasprint-amh/manifests/4.VEL/2035.json",
    "type": "Manifest",
    "label": {
        "nl": [
            "Plan van het fortress Nieuw Amsterdam."
        ]
    },
    "metadata": [
        {
            "label": {
                "nl": [
                    "Identifier"
                ]
            },
            "value": {
                "en": [
                    "2035"
                ]
            }
        },
        {
            "label": {
                "nl": [
                    "Date"
                ]
            },
            "value": {
                "en": [
                    "?"
                ]
            }
        },
        {
            "label": {
                "nl": [
                    "Permalink"
                ]
            },
            "value": {
                "en": [
                    "<a href=\"http://hdl.handle.net/10648/948da54e-0363-431f-9c05-0232f8938f51\">http://hdl.handle.net/10648/948da54e-0363-431f-9c05-0232f8938f51</a>"
                ]
            }
        },
        {
            "label": {
                "nl": [
                    "Metadata from the Atlas of Mutual Heritage"
                ]
            },
            "value": {
                "en": [
                    "\n        <strong>Title</strong>: Kaart van een nieuw ontwerp voor fort Nieuw Amsterdam<br>\n        <strong>Description</strong>: Titel Leupe: Plan van het fortress Nieuw Amsterdam.<br>Deze plattegrond van Nieuw Amsterdam is gemaakt toen de eerste grote gebreken tijdens de bouw aan het licht kwamen. Grote delen van het fort begonnen in de natte grond al gauw te verzakken, waaronder de hoofdsluis. De aantekening op deze anonieme, in 1741 overgezonden kaart maakt daarvan melding met betrekking tot de gemetselde waldoorgangen bij de brug; tevens is daar in summiere vorm de indeling binnen de wallen aangegeven.<br>Eind 1733 werd door de Staten-Generaal een overeenkomst tussen de Soci\u00ebteit van Suriname en de vertegenwoordigers van de kolonisten bekrachtigd tot het versterken van de verdediging van Suriname. Dit ontwerp voor fort Nieuw Amsterdam werd vermoedelijk kort hierop gemaakt. De daadwerkelijke bouw begon in 1736, bleek aanzienlijk moeilijker en bewerkelijker dan voorzien, en werd pas in 1747 voltooid. Ook daarna bleef het fort altijd problematisch in onderhoud en verdediging. (Zie voor meer details de titels onder 'documentatie', in het bijzonder die van Temminck Groll.)<br>Het noorden is links.<br>\n        <strong>URL</strong>: <a href=\"https://www.atlasofmutualheritage.nl/page/2021/kaart-van-een-nieuw-ontwerp-voor-fort-nieuw-amsterdam\">https://www.atlasofmutualheritage.nl/page/2021/kaart-van-een-nieuw-ontwerp-voor-fort-nieuw-amsterdam</a>\n        "
                ]
            }
        }
    ],
    "rights": "https://creativecommons.org/publicdomain/mark/1.0/",
    "seeAlso": [
        {
            "id": "https://globalise-huygens.github.io/datasprint-amh/aggregations/4.VEL/2035.json",
            "type": "ore:Aggregation"
        }
    ],
    "items": [
        {
            "id": "https://globalise-huygens.github.io/datasprint-amh/manifests/4.VEL/2035.json/canvas/p1",
            "type": "Canvas",
            "label": {
                "nl": [
                    "Plan van het fortress Nieuw Amsterdam."
                ]
            },
            "height": 3338,
            "width": 3270,
            "metadata": [
                {
                    "label": {
                        "nl": [
                            "Identifier"
                        ]
                    },
                    "value": {
                        "en": [
                            "2035"
                        ]
                    }
                },
                {
                    "label": {
                        "nl": [
                            "Date"
                        ]
                    },
                    "value": {
                        "en": [
                            "?"
                        ]
                    }
                },
                {
                    "label": {
                        "nl": [
                            "Permalink"
                        ]
                    },
                    "value": {
                        "en": [
                            "<a href=\"http://hdl.handle.net/10648/948da54e-0363-431f-9c05-0232f8938f51\">http://hdl.handle.net/10648/948da54e-0363-431f-9c05-0232f8938f51</a>"
                        ]
                    }
                },
                {
                    "label": {
                        "nl": [
                            "Metadata from the Atlas of Mutual Heritage"
                        ]
                    },
                    "value": {
                        "en": [
                            "\n        <strong>Title</strong>: Kaart van een nieuw ontwerp voor fort Nieuw Amsterdam<br>\n        <strong>Description</strong>: Titel Leupe: Plan van het fortress Nieuw Amsterdam.<br>Deze plattegrond van Nieuw Amsterdam is gemaakt toen de eerste grote gebreken tijdens de bouw aan het licht kwamen. Grote delen van het fort begonnen in de natte grond al gauw te verzakken, waaronder de hoofdsluis. De aantekening op deze anonieme, in 1741 overgezonden kaart maakt daarvan melding met betrekking tot de gemetselde waldoorgangen bij de brug; tevens is daar in summiere vorm de indeling binnen de wallen aangegeven.<br>Eind 1733 werd door de Staten-Generaal een overeenkomst tussen de Soci\u00ebteit van Suriname en de vertegenwoordigers van de kolonisten bekrachtigd tot het versterken van de verdediging van Suriname. Dit ontwerp voor fort Nieuw Amsterdam werd vermoedelijk kort hierop gemaakt. De daadwerkelijke bouw begon in 1736, bleek aanzienlijk moeilijker en bewerkelijker dan voorzien, en werd pas in 1747 voltooid. Ook daarna bleef het fort altijd problematisch in onderhoud en verdediging. (Zie voor meer details de titels onder 'documentatie', in het bijzonder die van Temminck Groll.)<br>Het noorden is links.<br>\n        <strong>URL</strong>: <a href=\"https://www.atlasofmutualheritage.nl/page/2021/kaart-van-een-nieuw-ontwerp-voor-fort-nieuw-amsterdam\">https://www.atlasofmutualheritage.nl/page/2021/kaart-van-een-nieuw-ontwerp-voor-fort-nieuw-amsterdam</a>\n        "
                        ]
                    }
                }
            ],
            "items": [
                {
                    "id": "https://globalise-huygens.github.io/datasprint-amh/manifests/4.VEL/2035.json/canvas/p1/annotationpage",
                    "type": "AnnotationPage",
                    "items": [
                        {
                            "id": "https://globalise-huygens.github.io/datasprint-amh/manifests/4.VEL/2035.json/canvas/p1/anno",
                            "type": "Annotation",
                            "motivation": "painting",
                            "body": {
                                "id": "https://service.archief.nl/iipsrv?IIIF=/ce/71/e0/0a/df/a9/48/33/91/09/af/cb/1f/3a/91/59/f71deb40-486f-4722-b16b-5150c7981d03.jp2/full/full/0/default.jpg",
                                "type": "Image",
                                "height": 3338,
                                "width": 3270,
                                "service": [
                                    {
                                        "@id": "https://service.archief.nl/iipsrv?IIIF=/ce/71/e0/0a/df/a9/48/33/91/09/af/cb/1f/3a/91/59/f71deb40-486f-4722-b16b-5150c7981d03.jp2",
                                        "@type": "ImageService2",
                                        "profile": "http://iiif.io/api/image/2/level1"
                                    }
                                ],
                                "format": "image/jpeg"
                            },
                            "target": "https://globalise-huygens.github.io/datasprint-amh/manifests/4.VEL/2035.json/canvas/p1"
                        }
                    ]
                }
            ]
        }
    ]
}