{
    "@context": "http://iiif.io/api/presentation/3/context.json",
    "id": "https://globalise-huygens.github.io/datasprint-amh/manifests/4.VEL/2083.json",
    "type": "Manifest",
    "label": {
        "nl": [
            "Plaan van defensie voor de Mottkreek."
        ]
    },
    "metadata": [
        {
            "label": {
                "nl": [
                    "Identifier"
                ]
            },
            "value": {
                "en": [
                    "2083"
                ]
            }
        },
        {
            "label": {
                "nl": [
                    "Date"
                ]
            },
            "value": {
                "en": [
                    "1793"
                ]
            }
        },
        {
            "label": {
                "nl": [
                    "Permalink"
                ]
            },
            "value": {
                "en": [
                    "<a href=\"http://hdl.handle.net/10648/a4101289-4e1d-42ac-912c-35eb2b51832d\"></a>"
                ]
            }
        },
        {
            "label": {
                "nl": [
                    "Metadata from the Atlas of Mutual Heritage"
                ]
            },
            "value": {
                "en": [
                    "\n    <strong>Title</strong>: Verdedigingsplan voor de Motkreek<br>\n    <strong>Description</strong>: Titel Leupe: Plaan van defensie voor de Mottkreek.<br>Deze kaart toont de zogenoemde Brandwacht aan de Motkreek, die in 1685 ingericht als uitkijkpost op de zeeroute langs de oostkust naar de monding van de Surinamerivier. In de latere achttiende eeuw bestond de Brandwacht uit een redoute aan de oostoever van de kreek op zo\u2019n driekwart kilometer van de monding, met een aparte piketpost aan het zeestrand. Deze projectkaart bestrijkt alleen het meest noordelijke deel van de kreek boven de nieuwe plantages en toont het ontwerp voor een nieuwe piketpost met defensielinie bij de monding. Het is niet bekend of het plan ook in deze vorm is uitgevoerd.<br>Het noorden is rechtsonder.<br>Schaalstok van 15 Kettingen a 66 Voeten Rhijnlands = [ca. 1 : 1.600].<br>\n    <strong>URL</strong>: <a href=\"https://www.atlasofmutualheritage.nl/page/7767/verdedigingsplan-voor-de-motkreek\">https://www.atlasofmutualheritage.nl/page/7767/verdedigingsplan-voor-de-motkreek</a>\n    "
                ]
            }
        }
    ],
    "rights": "https://creativecommons.org/publicdomain/mark/1.0/",
    "seeAlso": [
        {
            "id": "https://globalise-huygens.github.io/datasprint-amh/aggregations/4.VEL/2083.json",
            "type": "ore:Aggregation"
        }
    ],
    "items": [
        {
            "id": "https://globalise-huygens.github.io/datasprint-amh/manifests/4.VEL/2083.json/canvas/p1",
            "type": "Canvas",
            "height": 12306,
            "width": 8097,
            "items": [
                {
                    "id": "https://globalise-huygens.github.io/datasprint-amh/manifests/4.VEL/2083.json/canvas/p1/annotationpage",
                    "type": "AnnotationPage",
                    "items": [
                        {
                            "id": "https://globalise-huygens.github.io/datasprint-amh/manifests/4.VEL/2083.json/canvas/p1/anno",
                            "type": "Annotation",
                            "motivation": "painting",
                            "body": {
                                "id": "https://service.archief.nl/iipsrv?IIIF=/d5/9b/54/b0/e4/4a/43/18/9e/86/64/82/9c/d2/df/35/59b51f9c-6363-4e94-9cb6-0bb9ed5a49a9.jp2/full/full/0/default.jpg",
                                "type": "Image",
                                "height": 12306,
                                "width": 8097,
                                "service": [
                                    {
                                        "@id": "https://service.archief.nl/iipsrv?IIIF=/d5/9b/54/b0/e4/4a/43/18/9e/86/64/82/9c/d2/df/35/59b51f9c-6363-4e94-9cb6-0bb9ed5a49a9.jp2",
                                        "@type": "ImageService2",
                                        "profile": "http://iiif.io/api/image/2/level1"
                                    }
                                ],
                                "format": "image/jpeg"
                            },
                            "target": "https://globalise-huygens.github.io/datasprint-amh/manifests/4.VEL/2083.json/canvas/p1"
                        }
                    ]
                }
            ]
        }
    ]
}