{
    "@context": "http://iiif.io/api/presentation/3/context.json",
    "id": "https://globalise-huygens.github.io/datasprint-amh/manifests/4.VEL/751.json",
    "type": "Manifest",
    "label": {
        "nl": [
            "Het Fortress Hollandia tot Bokeshoe."
        ]
    },
    "metadata": [
        {
            "label": {
                "nl": [
                    "Identifier"
                ]
            },
            "value": {
                "none": [
                    "751"
                ]
            }
        },
        {
            "label": {
                "nl": [
                    "Date"
                ]
            },
            "value": {
                "none": [
                    "1791"
                ]
            }
        },
        {
            "label": {
                "nl": [
                    "Permalink"
                ]
            },
            "value": {
                "none": [
                    "<a href=\"http://hdl.handle.net/10648/55bb4e47-7536-427b-8e66-1ed92e5ceba0\"></a>"
                ]
            }
        }
    ],
    "rights": "https://creativecommons.org/publicdomain/mark/1.0/",
    "seeAlso": [
        {
            "id": "https://globalise-huygens.github.io/datasprint-amh/aggregations/4.VEL/751.json",
            "type": "ore:Aggregation"
        }
    ],
    "items": [
        {
            "id": "https://globalise-huygens.github.io/datasprint-amh/manifests/4.VEL/751.json#canvas/p1",
            "type": "Canvas",
            "height": 7929,
            "width": 5864,
            "items": [
                {
                    "id": "https://globalise-huygens.github.io/datasprint-amh/manifests/4.VEL/751.json#canvas/p1/annotationpage",
                    "type": "AnnotationPage",
                    "items": [
                        {
                            "id": "https://globalise-huygens.github.io/datasprint-amh/manifests/4.VEL/751.json#canvas/p1/anno",
                            "type": "Annotation",
                            "motivation": "painting",
                            "body": {
                                "id": "https://service.archief.nl/iipsrv?IIIF=/73/0c/1b/23/d3/ff/42/ce/b3/b9/5c/c0/74/c9/f6/d8/b66430ea-5bbe-4de8-a908-3046d002297e.jp2/full/full/0/default.jpg",
                                "type": "Image",
                                "height": 7929,
                                "width": 5864,
                                "service": [
                                    {
                                        "@id": "https://service.archief.nl/iipsrv?IIIF=/73/0c/1b/23/d3/ff/42/ce/b3/b9/5c/c0/74/c9/f6/d8/b66430ea-5bbe-4de8-a908-3046d002297e.jp2",
                                        "@type": "ImageService2",
                                        "profile": "http://iiif.io/api/image/2/level1"
                                    }
                                ],
                                "format": "image/jpeg"
                            },
                            "target": "https://globalise-huygens.github.io/datasprint-amh/manifests/4.VEL/751.json#canvas/p1"
                        }
                    ]
                }
            ]
        }
    ]
}