{
    "@context": "http://iiif.io/api/presentation/3/context.json",
    "id": "https://globalise-huygens.github.io/datasprint-amh/manifests/4.VEL/828.json",
    "type": "Manifest",
    "label": {
        "nl": [
            "Plan van 't Fort de Goede Hoop, 's Comp. Tuyn en eenige publique en particuliere gebouwen daaromtrent."
        ]
    },
    "metadata": [
        {
            "label": {
                "nl": [
                    "Identifier"
                ]
            },
            "value": {
                "en": [
                    "828"
                ]
            }
        },
        {
            "label": {
                "nl": [
                    "Date"
                ]
            },
            "value": {
                "en": [
                    "1600/1700"
                ]
            }
        },
        {
            "label": {
                "nl": [
                    "Permalink"
                ]
            },
            "value": {
                "en": [
                    "<a href=\"http://hdl.handle.net/10648/00758059-31f9-4c90-978a-daadd9741009\"></a>"
                ]
            }
        },
        {
            "label": {
                "nl": [
                    "Metadata from the Atlas of Mutual Heritage"
                ]
            },
            "value": {
                "en": [
                    "\n    <strong>Title</strong>: Plattegrond van het fort de Goede Hoop<br>\n    <strong>Description</strong>: Titel catalogus Leupe (NA): Plan van 't Fort de Goede Hoop, 's Comps. tuyn en eenige publique en particuliere gebouwen, daaromtrent.<br>Plattegrond van de tuinen, de particuliere en publieke gebouwen met aanduiding van de nieuwe herhuisvesting van particulieren na de gedwongen verplaatsing uit de nabije omgeving van het fort aan de Kaap.<br>Notities verso: A.A. nr. 5c, veros 498 x.<br>Legenda: A-Z<br>Topografische naam vermeld op deze kaart: Tafelbaij.<br>\n    <strong>URL</strong>: <a href=\"https://www.atlasofmutualheritage.nl/page/351/plattegrond-van-het-fort-de-goede-hoop\">https://www.atlasofmutualheritage.nl/page/351/plattegrond-van-het-fort-de-goede-hoop</a>\n    "
                ]
            }
        }
    ],
    "rights": "https://creativecommons.org/publicdomain/mark/1.0/",
    "seeAlso": [
        {
            "id": "https://globalise-huygens.github.io/datasprint-amh/aggregations/4.VEL/828.json",
            "type": "ore:Aggregation"
        }
    ],
    "items": [
        {
            "id": "https://globalise-huygens.github.io/datasprint-amh/manifests/4.VEL/828.json/canvas/p1",
            "type": "Canvas",
            "height": 6075,
            "width": 8476,
            "items": [
                {
                    "id": "https://globalise-huygens.github.io/datasprint-amh/manifests/4.VEL/828.json/canvas/p1/annotationpage",
                    "type": "AnnotationPage",
                    "items": [
                        {
                            "id": "https://globalise-huygens.github.io/datasprint-amh/manifests/4.VEL/828.json/canvas/p1/anno",
                            "type": "Annotation",
                            "motivation": "painting",
                            "body": {
                                "id": "https://service.archief.nl/iipsrv?IIIF=/5b/9f/77/e6/e2/d2/44/df/87/2b/0c/ea/4f/51/d2/d7/e53106f4-05be-47d5-a758-24ad5a0d1e47.jp2/full/full/0/default.jpg",
                                "type": "Image",
                                "height": 6075,
                                "width": 8476,
                                "service": [
                                    {
                                        "@id": "https://service.archief.nl/iipsrv?IIIF=/5b/9f/77/e6/e2/d2/44/df/87/2b/0c/ea/4f/51/d2/d7/e53106f4-05be-47d5-a758-24ad5a0d1e47.jp2",
                                        "@type": "ImageService2",
                                        "profile": "http://iiif.io/api/image/2/level1"
                                    }
                                ],
                                "format": "image/jpeg"
                            },
                            "target": "https://globalise-huygens.github.io/datasprint-amh/manifests/4.VEL/828.json/canvas/p1"
                        }
                    ]
                }
            ]
        }
    ]
}