{
    "@context": "http://iiif.io/api/presentation/3/context.json",
    "id": "https://globalise-huygens.github.io/datasprint-amh/manifests/4.VEL/867.json",
    "type": "Manifest",
    "label": {
        "nl": [
            "Gezigt op de Stad en omstreken van Diu."
        ]
    },
    "metadata": [
        {
            "label": {
                "nl": [
                    "Identifier"
                ]
            },
            "value": {
                "en": [
                    "867"
                ]
            }
        },
        {
            "label": {
                "nl": [
                    "Date"
                ]
            },
            "value": {
                "en": [
                    "1600/1700"
                ]
            }
        },
        {
            "label": {
                "nl": [
                    "Permalink"
                ]
            },
            "value": {
                "en": [
                    "<a href=\"http://hdl.handle.net/10648/58cc8d7d-a629-4c63-9729-9d73027aa59a\">http://hdl.handle.net/10648/58cc8d7d-a629-4c63-9729-9d73027aa59a</a>"
                ]
            }
        },
        {
            "label": {
                "nl": [
                    "Metadata from the Atlas of Mutual Heritage"
                ]
            },
            "value": {
                "en": [
                    "\n    <strong>Title</strong>: Plattegrond van Diu<br>\n    <strong>Description</strong>: Titel catalogus Leupe (NA): Gezigt op de Stad en omstreken van Diu.<br>Rechtsboven genummerd: 16.<br>Notities verso: 499 c<br>Legenda: A-Z; a<br>\n    <strong>URL</strong>: <a href=\"https://www.atlasofmutualheritage.nl/page/6706/plattegrond-van-diu\">https://www.atlasofmutualheritage.nl/page/6706/plattegrond-van-diu</a>\n    "
                ]
            }
        }
    ],
    "rights": "https://creativecommons.org/publicdomain/mark/1.0/",
    "seeAlso": [
        {
            "id": "https://globalise-huygens.github.io/datasprint-amh/aggregations/4.VEL/867.json",
            "type": "ore:Aggregation"
        }
    ],
    "items": [
        {
            "id": "https://globalise-huygens.github.io/datasprint-amh/manifests/4.VEL/867.json/canvas/p1",
            "type": "Canvas",
            "height": 6319,
            "width": 8704,
            "items": [
                {
                    "id": "https://globalise-huygens.github.io/datasprint-amh/manifests/4.VEL/867.json/canvas/p1/annotationpage",
                    "type": "AnnotationPage",
                    "items": [
                        {
                            "id": "https://globalise-huygens.github.io/datasprint-amh/manifests/4.VEL/867.json/canvas/p1/anno",
                            "type": "Annotation",
                            "motivation": "painting",
                            "body": {
                                "id": "https://service.archief.nl/iipsrv?IIIF=/02/2f/51/45/be/9d/4f/c9/95/35/13/2a/ee/18/e7/82/03c5e6be-6aae-4a88-be25-3dba68a4472a.jp2/full/full/0/default.jpg",
                                "type": "Image",
                                "height": 6319,
                                "width": 8704,
                                "service": [
                                    {
                                        "@id": "https://service.archief.nl/iipsrv?IIIF=/02/2f/51/45/be/9d/4f/c9/95/35/13/2a/ee/18/e7/82/03c5e6be-6aae-4a88-be25-3dba68a4472a.jp2",
                                        "@type": "ImageService2",
                                        "profile": "http://iiif.io/api/image/2/level1"
                                    }
                                ],
                                "format": "image/jpeg"
                            },
                            "target": "https://globalise-huygens.github.io/datasprint-amh/manifests/4.VEL/867.json/canvas/p1"
                        }
                    ]
                }
            ]
        }
    ]
}