{
    "@context": "https://globalise-huygens.github.io/datasprint-amh/context.json",
    "id": "https://globalise-huygens.github.io/datasprint-amh/aggregations/4.VEL/1506.json",
    "type": "ore:Aggregation",
    "edm:aggregatedCHO": {
        "id": "http://hdl.handle.net/10648/d97fc0a6-6a16-4a3d-b4ca-f53b035ab601",
        "type": [
            "edm:ProvidedCHO",
            "schema:Map"
        ],
        "image": "https://www.atlasofmutualheritage.nl/image/2022/4/21/nl_hana_4_vel_1506.jpg%28mediaclass-meta-tag-image.4b190bfcc55e159332679890b17bd2261ced7954%29.jpg",
        "dc:title": "Plankaart van de mondingen van de Demerary en de Essequibo met bestaande en nieuw aan te leggen plantages",
        "dc:description": "Titel Leupe: Kaart van de Westwal der rivier Demerary en de daaraan gelegene plantages.\nKaart van de mondingen van de Demerary en de Essequibo, met daarop plantages en forten alsmede een grootschalig plan tot plantageaanleg tussen de twee rivieren. De namen van deel van de bestaande plantages staan in de percelen geschreven.\nOnderdeel van een serie plannen voor de verdere ontwikkeling van de kolonie in de jaren \u201970 en \u201980 van de 18de eeuw.\nRechtsboven \u2018Nr. 5, plan I\u2019\nSchaalstok van 2000 Rijnlandse Roeden.",
        "dc:type": "tekening",
        "dc:identifier": "VEL1506",
        "dc:subject": [
            "landerij / plantage",
            "plattegrond / kaart"
        ],
        "dc:language": "nl",
        "dcterms:medium": "papier",
        "edmfp:technique": "pen",
        "dcterms:provenance": "Nationaal Archief",
        "dcterms:isPartOf": "Atlas of Mutual Heritage",
        "seeAlso": "https://www.atlasofmutualheritage.nl/page/9386/plankaart-van-de-mondingen-van-de-demerary-en-de-essequibo-met"
    },
    "edm:isShownBy": {
        "id": "https://service.archief.nl/iip/e3/b8/69/3c/d6/50/4e/94/9d/4b/d1/2c/6d/a8/0f/cb/d6aec838-9646-4789-be80-93336127f179.jp2/full/full/0/default.jpg",
        "type": "edm:WebResource",
        "svcs:has_service": {
            "id": "https://service.archief.nl/iip/e3/b8/69/3c/d6/50/4e/94/9d/4b/d1/2c/6d/a8/0f/cb/d6aec838-9646-4789-be80-93336127f179.jp2",
            "type": "svcs:Service",
            "profile": "http://iiif.io/api/image",
            "implements": "http://iiif.io/api/image/2/level1.json"
        },
        "rights": "https://creativecommons.org/publicdomain/mark/1.0/",
        "isReferencedBy": {
            "id": "https://globalise-huygens.github.io/datasprint-amh/manifests/4.VEL/1506.json",
            "type": "iiif:Manifest",
            "rdfs:label": "1e exemplaar"
        }
    },
    "edm:dataProvider": "Rijksdienst voor het Cultureel Erfgoed",
    "edm:provider": "Nationaal Archief",
    "edm:rights": "https://creativecommons.org/publicdomain/mark/1.0/"
}