{
    "@context": "https://globalise-huygens.github.io/datasprint-amh/context.json",
    "id": "https://globalise-huygens.github.io/datasprint-amh/aggregations/4.VEL/459.json",
    "type": "ore:Aggregation",
    "edm:aggregatedCHO": {
        "id": "http://hdl.handle.net/10648/8ff90d76-76b8-45ca-be03-fbce443a01c5",
        "type": [
            "edm:ProvidedCHO",
            "schema:Map"
        ],
        "image": "https://www.atlasofmutualheritage.nl/image/2022/4/21/vel0459.jpg%28mediaclass-meta-tag-image.4b190bfcc55e159332679890b17bd2261ced7954%29.jpg",
        "dc:title": "Kaart van de westkust van Celebes",
        "dc:description": "Titel in catalogus Leupe (NA): Kaart van de Westkust van Celebes, de Oosthoek van Borneo, alsmede de eilanden gelegen tusschen de Oosthoek van Java tot aan de Straat Saleyer.\nRechtsboven genummerd: 10.\nNotities verso: De eijlanden ende gronden tusschen Macasser ende de Oost-kust van Java / H=17 [?] kust van Celebes / Damiate kamer A'dam 1674 [in potlood, met achter 1674 nog een onleesbaar woord] / 's ryks archief. [stempeltje].",
        "dc:type": "tekening",
        "dc:identifier": "VEL0459",
        "dc:subject": [
            "plattegrond / kaart",
            "kompas / windroos"
        ],
        "dc:language": "nl",
        "dcterms:medium": "papier",
        "edmfp:technique": "ingekleurde tekening",
        "dcterms:extent": "53 x 74,5 cm",
        "dcterms:date": "ca. 1695",
        "dcterms:provenance": "Nationaal Archief",
        "dcterms:isPartOf": "Atlas of Mutual Heritage",
        "seeAlso": "https://www.atlasofmutualheritage.nl/page/3810/kaart-van-de-westkust-van-celebes"
    },
    "edm:isShownBy": {
        "id": "https://service.archief.nl/iip/7a/da/df/28/5f/f4/47/4d/8e/c4/2c/c1/89/3d/42/80/260e1dd7-f9e7-46c5-bca4-0674ca30335c.jp2/full/full/0/default.jpg",
        "type": "edm:WebResource",
        "svcs:has_service": {
            "id": "https://service.archief.nl/iip/7a/da/df/28/5f/f4/47/4d/8e/c4/2c/c1/89/3d/42/80/260e1dd7-f9e7-46c5-bca4-0674ca30335c.jp2",
            "type": "svcs:Service",
            "profile": "http://iiif.io/api/image",
            "implements": "http://iiif.io/api/image/2/level1.json"
        },
        "rights": "https://creativecommons.org/publicdomain/mark/1.0/",
        "isReferencedBy": {
            "id": "https://globalise-huygens.github.io/datasprint-amh/manifests/4.VEL/459.json",
            "type": "iiif:Manifest",
            "rdfs:label": "Kaart van de Westkust van Celebes, de Oosthoek van Borneo, alsmede de eilanden gelegen tusschen de Oosthoek van Java tot aan Straat Saleyer."
        }
    },
    "edm:dataProvider": "Rijksdienst voor het Cultureel Erfgoed",
    "edm:provider": "Nationaal Archief",
    "edm:rights": "https://creativecommons.org/publicdomain/mark/1.0/"
}